RusticFS-0.1.5.dist-info/METADATA
RusticFS-0.1.5.dist-info/WHEEL
RusticFS/__init__.py
RusticFS/__init__.pyi
RusticFS/py.typed
RusticFS/RusticFS.cpython-311-darwin.so
RusticFS-0.1.5.dist-info/RECORD
