Metadata-Version: 2.3
Name: RusticFS
Version: 0.1.5
Classifier: Programming Language :: Rust
Classifier: Programming Language :: Python :: Implementation :: CPython
Classifier: Programming Language :: Python :: Implementation :: PyPy
Requires-Dist: cffi
Summary: A Rustic mockup File System running on top of a real file system
Author: Tosic.Killer <emil.schutt@gmail.com>
Author-email: Tosic.Killer <emil.schutt@gmail.com>
License: MIT
Requires-Python: >=3.7
